Workbook

Sheet Inputs
B2: AI Engineering ROI Calculator
B3: Companion to Software Engineering with AI by Ryan Byrd · Ch 54 §54.5
B5: How to use this model
B6: Fill in the BLUE cells with your numbers. Black cells are formulas; do not edit. Yellow-highlighted cells are the key assumptions to revisit quarterly. Three scenarios (Conservative / Base / Aggressive) are computed automatically. Sensitivity analysis on the next sheet shows how ROI moves with the productivity gain assumption.
B9: Engineering org parameters
C10: Conservative | D10: Base | E10: Aggressive
B11: Total engineers (full org, AI users + non-users) | C11: 60 | D11: 60 | E11: 60 | F11: Headcount as of plan date. Use total org, not just AI users.
B12: Loaded cost per engineer ($/year) | C12: 220000 | D12: 240000 | E12: 260000 | F12: Salary + benefits + overhead. Mid-size US 2026 typically $200K-$280K.
B13: Coding utilization factor | C13: 0.55 | D13: 0.6 | E13: 0.65 | F13: Fraction of eng time on coding (vs meetings, support, on-call). Typical: 0.55-0.70.
B14: AI tool adoption rate | C14: 0.6 | D14: 0.8 | E14: 0.95 | F14: Fraction of eligible engineers actively using AI tooling >2x/week.
B15: Productivity gain on AI-assisted work | C15: 0.08 | D15: 0.12 | E15: 0.18 | F15: Year 1: 5-15% prepared teams. Above 15% requires very mature harness.
B17: Annual cost inputs ($/year)
C18: Conservative | D18: Base | E18: Aggressive
B19: Tooling spend (per-seat licenses, annual) | C19: 90000 | D19: 130000 | E19: 180000 | F19: Cursor / Copilot / Claude Code seats × N. Scale with adoption.
B20: Token / API spend (annual) | C20: 60000 | D20: 95000 | E20: 145000 | F20: Per-dev median × weeks × adopters. Higher with more agentic use.
B21: Harness investment (engineer time) | C21: 80000 | D21: 120000 | E21: 200000 | F21: FTE equivalent. 0.5 FTE for 60-eng org typical.
B22: Governance overhead (CISO, GC, legal) | C22: 20000 | D22: 30000 | E22: 50000 | F22: Vendor reviews, customer Q&A, audits. Annual.
B25: ROI calculation
C26: Conservative | D26: Base | E26: Aggressive
B27: Annual productivity gain ($) | C27: =C11*C12*C13*C14*C15 -> 348480 | D27: =D11*D12*D13*D14*D15 -> 829440 | E27: =E11*E12*E13*E14*E15 -> 1733940 | F27: Formula: engineers × loaded cost × utilization × adoption × productivity gain
B28: Total annual cost ($) | C28: =SUM(C19:C22) -> 250000 | D28: =SUM(D19:D22) -> 375000 | E28: =SUM(E19:E22) -> 575000 | F28: Tooling + Tokens + Harness + Governance
B29: Net ROI ($) | C29: =C27-C28 -> 98480 | D29: =D27-D28 -> 454440 | E29: =E27-E28 -> 1158940
B30: ROI multiple (gain ÷ cost) | C30: =C27/C28 -> 1.39392 | D30: =D27/D28 -> 2.21184 | E30: =E27/E28 -> 3.0155478
B31: Per-engineer net ROI ($) | C31: =C29/C11 -> 1641.3333 | D31: =D29/D11 -> 7574 | E31: =E29/E11 -> 19315.667
B34: Notes for the CFO conversation
B35: • Productivity gain is the most sensitive input. Each 1% is roughly $90K at 60 engineers. See Sensitivity sheet.
B36: • Adoption rate is the second most sensitive. Realistic mid-size adoption is 60-80% in year 1.
B37: • Token spend can swing 2-3x based on routing discipline (Sonnet vs Opus, retry control).
B38: • Harness investment as engineer time is real cost; do not exclude it just because it's not a separate line item.
B39: • Year 2 economics improve materially as harness compounds. This model is year 1.
B40: • Substitution posture (cuts + AI) requires modifying the productivity gain assumption downward.

Sheet Sensitivity
B2: Sensitivity Analysis — Net ROI by Productivity Gain
B3: Reads from Inputs!Base case for everything except productivity gain (varied across columns).
B6: Productivity gain → | C6: 0.05 | D6: 0.08 | E6: 0.1 | F6: 0.12 | G6: 0.15 | H6: 0.18 | I6: 0.2 | J6: 0.25
B8: Productivity gain ($) | C8: =Inputs!D11*Inputs!D12*Inputs!D13*Inputs!D14*C6 -> 345600 | D8: =Inputs!D11*Inputs!D12*Inputs!D13*Inputs!D14*D6 -> 552960 | E8: =Inputs!D11*Inputs!D12*Inputs!D13*Inputs!D14*E6 -> 691200 | F8: =Inputs!D11*Inputs!D12*Inputs!D13*Inputs!D14*F6 -> 829440 | G8: =Inputs!D11*Inputs!D12*Inputs!D13*Inputs!D14*G6 -> 1036800 | H8: =Inputs!D11*Inputs!D12*Inputs!D13*Inputs!D14*H6 -> 1244160 | I8: =Inputs!D11*Inputs!D12*Inputs!D13*Inputs!D14*I6 -> 1382400 | J8: =Inputs!D11*Inputs!D12*Inputs!D13*Inputs!D14*J6 -> 1728000
B9: Total cost ($) | C9: =SUM(Inputs!D19:D22) -> 375000 | D9: =SUM(Inputs!D19:D22) -> 375000 | E9: =SUM(Inputs!D19:D22) -> 375000 | F9: =SUM(Inputs!D19:D22) -> 375000 | G9: =SUM(Inputs!D19:D22) -> 375000 | H9: =SUM(Inputs!D19:D22) -> 375000 | I9: =SUM(Inputs!D19:D22) -> 375000 | J9: =SUM(Inputs!D19:D22) -> 375000
B10: Net ROI ($) | C10: =C8-C9 -> -29400 | D10: =D8-D9 -> 177960 | E10: =E8-E9 -> 316200 | F10: =F8-F9 -> 454440 | G10: =G8-G9 -> 661800 | H10: =H8-H9 -> 869160 | I10: =I8-I9 -> 1007400 | J10: =J8-J9 -> 1353000
B11: ROI multiple | C11: =C8/C9 -> 0.9216 | D11: =D8/D9 -> 1.47456 | E11: =E8/E9 -> 1.8432 | F11: =F8/F9 -> 2.21184 | G11: =G8/G9 -> 2.7648 | H11: =H8/H9 -> 3.31776 | I11: =I8/I9 -> 3.6864 | J11: =J8/J9 -> 4.608
B14: How to read this
B16: • Each column is a scenario where productivity gain is the only thing that changes; all other Base assumptions hold.
B17: • If your honest measured productivity gain is below 8%, you may not be net-positive. Audit cost discipline first.
B18: • Above 15%, claims start to need exceptional evidence. Most mid-size teams should plan for 8-15% in year 1.
B19: • The relationship is roughly linear — each 1% of productivity gain adds ~$90K to net ROI at 60 engineers.

Sheet Forecast
B2: 12-Month Token Spend Forecast
B3: Reads from Inputs sheet. Edit Inputs to update.
B6: Month | C6: M1 | D6: M2 | E6: M3 | F6: M4 | G6: M5 | H6: M6 | I6: M7 | J6: M8 | K6: M9 | L6: M10 | M6: M11 | N6: M12 | O6: Annual
B8: Conservative scenario
B9: Monthly token spend ($) | C9: =Inputs!C20/12*0.5 -> 2500 | D9: =Inputs!C20/12*0.58 -> 2900 | E9: =Inputs!C20/12*0.67 -> 3350 | F9: =Inputs!C20/12*0.75 -> 3750 | G9: =Inputs!C20/12*0.83 -> 4150 | H9: =Inputs!C20/12*0.92 -> 4600 | I9: =Inputs!C20/12*1 -> 5000 | J9: =Inputs!C20/12*1 -> 5000 | K9: =Inputs!C20/12*1 -> 5000 | L9: =Inputs!C20/12*1 -> 5000 | M9: =Inputs!C20/12*1 -> 5000 | N9: =Inputs!C20/12*1 -> 5000 | O9: =SUM(C9:N9) -> 51250
B10: Cumulative ($) | C10: =C9 -> 2500 | D10: =C10+D9 -> 5400 | E10: =D10+E9 -> 8750 | F10: =E10+F9 -> 12500 | G10: =F10+G9 -> 16650 | H10: =G10+H9 -> 21250 | I10: =H10+I9 -> 26250 | J10: =I10+J9 -> 31250 | K10: =J10+K9 -> 36250 | ... N10: =M10+N9 -> 51250
B12: Base scenario
B13: Monthly token spend ($) | C13: =Inputs!D20/12*0.5 -> 3958.3333 | D13: =Inputs!D20/12*0.58 -> 4591.6667 | E13: =Inputs!D20/12*0.67 -> 5304.1667 | F13: =Inputs!D20/12*0.75 -> 5937.5 | G13: =Inputs!D20/12*0.83 -> 6570.8333 | H13: =Inputs!D20/12*0.92 -> 7283.3333 | I13: =Inputs!D20/12*1 -> 7916.6667 | J13: =Inputs!D20/12*1 -> 7916.6667 | K13: =Inputs!D20/12*1 -> 7916.6667 | L13: =Inputs!D20/12*1 -> 7916.6667 | M13: =Inputs!D20/12*1 -> 7916.6667 | N13: =Inputs!D20/12*1 -> 7916.6667 | O13: =SUM(C13:N13) -> 81145.833
B14: Cumulative ($) | C14: =C13 -> 3958.3333 | D14: =C14+D13 -> 8550 | E14: =D14+E13 -> 13854.167 | F14: =E14+F13 -> 19791.667 | G14: =F14+G13 -> 26362.5 | H14: =G14+H13 -> 33645.833 | I14: =H14+I13 -> 41562.5 | J14: =I14+J13 -> 49479.167 | K14: =J14+K13 -> 57395.833 | ... N14: =M14+N13 -> 81145.833
B16: Aggressive scenario
B17: Monthly token spend ($) | C17: =Inputs!E20/12*0.5 -> 6041.6667 | D17: =Inputs!E20/12*0.58 -> 7008.3333 | E17: =Inputs!E20/12*0.67 -> 8095.8333 | F17: =Inputs!E20/12*0.75 -> 9062.5 | G17: =Inputs!E20/12*0.83 -> 10029.167 | H17: =Inputs!E20/12*0.92 -> 11116.667 | I17: =Inputs!E20/12*1 -> 12083.333 | J17: =Inputs!E20/12*1 -> 12083.333 | K17: =Inputs!E20/12*1 -> 12083.333 | L17: =Inputs!E20/12*1 -> 12083.333 | M17: =Inputs!E20/12*1 -> 12083.333 | N17: =Inputs!E20/12*1 -> 12083.333 | O17: =SUM(C17:N17) -> 123854.17
B18: Cumulative ($) | C18: =C17 -> 6041.6667 | D18: =C18+D17 -> 13050 | E18: =D18+E17 -> 21145.833 | F18: =E18+F17 -> 30208.333 | G18: =F18+G17 -> 40237.5 | H18: =G18+H17 -> 51354.167 | I18: =H18+I17 -> 63437.5 | J18: =I18+J17 -> 75520.833 | K18: =J18+K17 -> 87604.167 | ... N18: =M18+N17 -> 123854.17
B22: Notes
B23: • Forecast assumes a linear ramp from 50% to 100% of full token spend over the first 6 months. Adjust if your rollout is faster or slower.
B24: • Add 15% buffer on top for batch workloads (test generation runs, mass refactors) not captured in per-developer median.
B25: • If batch workloads are large in your org, model them as separate line items above.
